{
  "name": "Stock Item 4 Name",
  "type": "Stock Item 4 Type",
  "power": "Stock Item 4 Power",
  "brand": "Stock Item 4 Brand",
  "model": "Stock Item 4 Model",
  "status": "RENTED",
  "numberOfUses": 45,
  "lastMaintenance": "2024-04-04",
  "acquisitionDate": "2020-07-04",
  "needsMaintenance": false,
  "imageURL": "imageURL",
  "rentValue": 400.50,
  "replacementCost": 4000.50,
  "pressure": "2000",
  "throughput": "450",
  "voltage": "110",
  "serialNumber": "3215462",
  "code": "334434254",
  "active": true,
  "comment": "Comment about Stock Item 4",
  "statusComment": "Just purchased. Sending straight to inventory",
  "supplierId": 4
}